LICENSE
MANIFEST.in
README.rst
screenshot.png
setup.py
i3_output_selector/__init__.py
i3_output_selector/__main__.py
i3_output_selector.egg-info/PKG-INFO
i3_output_selector.egg-info/SOURCES.txt
i3_output_selector.egg-info/dependency_links.txt
i3_output_selector.egg-info/entry_points.txt
i3_output_selector.egg-info/requires.txt
i3_output_selector.egg-info/top_level.txt