Metadata-Version: 1.1
Name: i3-output-selector
Version: 0.1.2
Summary: GUI tool to change output for the current workspace in i3.
Home-page: https://github.com/kwarunek/i3-output-selector
Author: Krzysztof Warunek
Author-email: krzysztof@warunek.net
License: MIT
Keywords: i3,workspace,selector,output
Platform: UNKNOWN
Classifier: License :: OSI Approved :: MIT License
Classifier: Programming Language :: Python :: 3
Classifier: Programming Language :: Python :: 2
Classifier: Operating System :: POSIX
Classifier: Development Status :: 3 - Alpha
